{
  "openapi": "3.1.0",
  "info": {
    "title": "ExoDB",
    "description": "Exoplanet and space exploration knowledge base covering exoplanets, missions, telescopes, astrobiology, space mining, planetary science, and space habitats",
    "version": "1.0.0",
    "contact": {
      "email": "61960005@qq.com"
    }
  },
  "servers": [
    {
      "url": "https://exo.genetech.tools"
    }
  ],
  "paths": {
    "/api/data.json": {
      "get": {
        "summary": "Get all ExoDB data",
        "description": "Returns complete structured data for 地外科学知识引擎",
        "responses": {
          "200": {
            "description": "Structured knowledge base data"
          }
        }
      }
    },
    "/api/entities.json": {
      "get": {
        "summary": "Get all entities",
        "description": "Returns flat list of all entities across categories",
        "responses": {
          "200": {
            "description": "Entity list"
          }
        }
      }
    }
  }
}